adtree/__init__.py
adtree/analysers.py
adtree/models.py
adtree/renderer.py
adtree/themes.py
adtree_viz-0.0.10.dist-info/LICENSE
adtree_viz-0.0.10.dist-info/METADATA
adtree_viz-0.0.10.dist-info/WHEEL
adtree_viz-0.0.10.dist-info/top_level.txt
adtree_viz-0.0.10.dist-info/RECORD
