Metadata-Version: 2.1
Name: adtree-viz
Version: 0.0.10
Summary: adtree-viz
Home-page: https://github.com/julianghionoiu/adtree-viz
Download-URL: https://github.com/julianghionoiu/adtree-viz/archive/v0.0.10.tar.gz
Author: Julian Ghionoiu
Author-email: julian.ghionoiu@gmail.com
Keywords: attack-defence,adtree
License-File: LICENSE
Requires-Dist: graphviz (==0.16)
